{
  "title": "Trek chez l'habitant au Népal, au fil des villages Sherpas",
  "slug": "trek-chez-lhabitant-nepal",
  "iso": "NP",
  "imgSrc2": {
    "src": "/images/voyages/trek-chez-lhabitant-nepal/CBFPoeCsQLumCFzRoq9e.jpg",
    "alt": "CBFPoeCsQLumCFzRoq9e"
  },
  "imgSrc1": {
    "src": "/images/voyages/trek-chez-lhabitant-nepal/xKaHUfWTQwes3RCnlr5J.jpg",
    "alt": "xKaHUfWTQwes3RCnlr5J"
  },
  "country": "Népal",
  "zoneChapka": 3,
  "privatisationAvailable": false,
  "groupeAvailable": true,
  "duration": "14 jours / 13 nuits",
  "startingPrice": 1460,
  "rating": 4.9,
  "comments": 17,
  "tooltipChild": "Dès 18 ans",
  "tooltipGroup": "Disponible en groupe",
  "dates": [
    {
      "departureDate": "2026-02-08T00:00:00",
      "returnDate": "2026-02-21T00:00:00",
      "startingPrice": 1470,
      "indivRoomPrice": 300,
      "maxTravellers": 8,
      "bookedPlaces": 0,
      "earlyBird": false,
      "promoEarlyBird": 0,
      "lastMinute": false,
      "promoLastMinute": 0,
      "promo": 0,
      "privatized": false,
      "flyTicketPrice": 0
    },
    {
      "departureDate": "2025-03-16T00:00:00",
      "returnDate": "2025-03-29T00:00:00",
      "startingPrice": 1460,
      "indivRoomPrice": 300,
      "maxTravellers": 8,
      "bookedPlaces": 4,
      "earlyBird": false,
      "promoEarlyBird": 0,
      "lastMinute": false,
      "promoLastMinute": 0,
      "promo": 0,
      "privatized": false,
      "flyTicketPrice": 0
    },
    {
      "departureDate": "2025-03-23T00:00:00",
      "returnDate": "2025-04-05T00:00:00",
      "startingPrice": 1460,
      "indivRoomPrice": 300,
      "maxTravellers": 8,
      "bookedPlaces": 4,
      "earlyBird": false,
      "promoEarlyBird": 0,
      "lastMinute": false,
      "promoLastMinute": 0,
      "promo": 0,
      "privatized": false,
      "flyTicketPrice": 0
    },
    {
      "departureDate": "2025-03-30T00:00:00",
      "returnDate": "2025-04-12T00:00:00",
      "startingPrice": 1460,
      "indivRoomPrice": 300,
      "maxTravellers": 8,
      "bookedPlaces": 4,
      "earlyBird": false,
      "promoEarlyBird": 0,
      "lastMinute": false,
      "promoLastMinute": 0,
      "promo": 0,
      "privatized": false,
      "flyTicketPrice": 0
    },
    {
      "departureDate": "2025-04-06T00:00:00",
      "returnDate": "2025-04-19T00:00:00",
      "startingPrice": 1460,
      "indivRoomPrice": 300,
      "maxTravellers": 8,
      "bookedPlaces": 6,
      "earlyBird": false,
      "promoEarlyBird": 0,
      "lastMinute": false,
      "promoLastMinute": 0,
      "promo": 0,
      "privatized": false,
      "flyTicketPrice": 0
    },
    {
      "departureDate": "2025-04-13T00:00:00",
      "returnDate": "2025-04-26T00:00:00",
      "startingPrice": 1460,
      "indivRoomPrice": 300,
      "maxTravellers": 8,
      "bookedPlaces": 3,
      "earlyBird": false,
      "promoEarlyBird": 0,
      "lastMinute": false,
      "promoLastMinute": 0,
      "promo": 0,
      "privatized": false,
      "flyTicketPrice": 0
    },
    {
      "departureDate": "2025-04-20T00:00:00",
      "returnDate": "2025-05-03T00:00:00",
      "startingPrice": 1460,
      "indivRoomPrice": 300,
      "maxTravellers": 8,
      "bookedPlaces": 0,
      "earlyBird": false,
      "promoEarlyBird": 0,
      "lastMinute": false,
      "promoLastMinute": 0,
      "promo": 0,
      "privatized": false,
      "flyTicketPrice": 0
    },
    {
      "departureDate": "2025-04-27T00:00:00",
      "returnDate": "2025-05-10T00:00:00",
      "startingPrice": 1460,
      "indivRoomPrice": 300,
      "maxTravellers": 8,
      "bookedPlaces": 6,
      "earlyBird": false,
      "promoEarlyBird": 0,
      "lastMinute": false,
      "promoLastMinute": 0,
      "promo": 0,
      "privatized": false,
      "flyTicketPrice": 0
    },
    {
      "departureDate": "2025-05-04T00:00:00",
      "returnDate": "2025-05-17T00:00:00",
      "startingPrice": 1460,
      "indivRoomPrice": 300,
      "maxTravellers": 8,
      "bookedPlaces": 5,
      "earlyBird": false,
      "promoEarlyBird": 0,
      "lastMinute": false,
      "promoLastMinute": 0,
      "promo": 0,
      "privatized": false,
      "flyTicketPrice": 0
    },
    {
      "departureDate": "2025-10-12T00:00:00",
      "returnDate": "2025-10-25T00:00:00",
      "startingPrice": 1460,
      "indivRoomPrice": 300,
      "maxTravellers": 8,
      "bookedPlaces": 0,
      "earlyBird": false,
      "promoEarlyBird": 0,
      "lastMinute": false,
      "promoLastMinute": 0,
      "promo": 0,
      "privatized": false,
      "flyTicketPrice": 0
    },
    {
      "departureDate": "2025-10-19T00:00:00",
      "returnDate": "2025-11-01T00:00:00",
      "startingPrice": 1460,
      "indivRoomPrice": 300,
      "maxTravellers": 8,
      "bookedPlaces": 0,
      "earlyBird": false,
      "promoEarlyBird": 0,
      "lastMinute": false,
      "promoLastMinute": 0,
      "promo": 0,
      "privatized": false,
      "flyTicketPrice": 0
    },
    {
      "departureDate": "2025-10-26T00:00:00",
      "returnDate": "2025-11-08T00:00:00",
      "startingPrice": 1460,
      "indivRoomPrice": 300,
      "maxTravellers": 8,
      "bookedPlaces": 3,
      "earlyBird": false,
      "promoEarlyBird": 0,
      "lastMinute": false,
      "promoLastMinute": 0,
      "promo": 0,
      "privatized": false,
      "flyTicketPrice": 0
    },
    {
      "departureDate": "2025-11-02T00:00:00",
      "returnDate": "2025-11-15T00:00:00",
      "startingPrice": 1460,
      "indivRoomPrice": 300,
      "maxTravellers": 8,
      "bookedPlaces": 5,
      "earlyBird": false,
      "promoEarlyBird": 0,
      "lastMinute": false,
      "promoLastMinute": 0,
      "promo": 0,
      "privatized": false,
      "flyTicketPrice": 0
    },
    {
      "departureDate": "2025-11-09T00:00:00",
      "returnDate": "2025-11-22T00:00:00",
      "startingPrice": 1460,
      "indivRoomPrice": 300,
      "maxTravellers": 8,
      "bookedPlaces": 4,
      "earlyBird": false,
      "promoEarlyBird": 0,
      "lastMinute": false,
      "promoLastMinute": 0,
      "promo": 0,
      "privatized": false,
      "flyTicketPrice": 0
    },
    {
      "departureDate": "2025-11-16T00:00:00",
      "returnDate": "2025-11-29T00:00:00",
      "startingPrice": 1460,
      "indivRoomPrice": 300,
      "maxTravellers": 8,
      "bookedPlaces": 7,
      "earlyBird": false,
      "promoEarlyBird": 0,
      "lastMinute": false,
      "promoLastMinute": 0,
      "promo": 0,
      "privatized": false,
      "flyTicketPrice": 0
    },
    {
      "departureDate": "2025-11-30T00:00:00",
      "returnDate": "2025-12-13T00:00:00",
      "startingPrice": 1460,
      "indivRoomPrice": 300,
      "maxTravellers": 8,
      "bookedPlaces": 0,
      "earlyBird": false,
      "promoEarlyBird": 0,
      "lastMinute": false,
      "promoLastMinute": 0,
      "promo": 0,
      "privatized": false,
      "flyTicketPrice": 0
    },
    {
      "departureDate": "2025-12-22T00:00:00",
      "returnDate": "2026-01-04T00:00:00",
      "startingPrice": 1460,
      "indivRoomPrice": 300,
      "maxTravellers": 8,
      "bookedPlaces": 0,
      "earlyBird": false,
      "promoEarlyBird": 0,
      "lastMinute": false,
      "promoLastMinute": 0,
      "promo": 0,
      "privatized": false,
      "flyTicketPrice": 0
    },
    {
      "departureDate": "2026-02-15T00:00:00",
      "returnDate": "2026-02-28T00:00:00",
      "startingPrice": 1470,
      "indivRoomPrice": 300,
      "maxTravellers": 8,
      "bookedPlaces": 0,
      "earlyBird": false,
      "promoEarlyBird": 0,
      "lastMinute": false,
      "promoLastMinute": 0,
      "promo": 0,
      "privatized": false,
      "flyTicketPrice": 0
    },
    {
      "departureDate": "2026-02-22T00:00:00",
      "returnDate": "2026-03-07T00:00:00",
      "startingPrice": 1470,
      "indivRoomPrice": 300,
      "maxTravellers": 8,
      "bookedPlaces": 0,
      "earlyBird": false,
      "promoEarlyBird": 0,
      "lastMinute": false,
      "promoLastMinute": 0,
      "promo": 0,
      "privatized": false,
      "flyTicketPrice": 0
    },
    {
      "departureDate": "2026-03-01T00:00:00",
      "returnDate": "2026-03-14T00:00:00",
      "startingPrice": 1470,
      "indivRoomPrice": 300,
      "maxTravellers": 8,
      "bookedPlaces": 0,
      "earlyBird": false,
      "promoEarlyBird": 0,
      "lastMinute": false,
      "promoLastMinute": 0,
      "promo": 0,
      "privatized": false,
      "flyTicketPrice": 0
    },
    {
      "departureDate": "2026-03-08T00:00:00",
      "returnDate": "2026-03-21T00:00:00",
      "startingPrice": 1470,
      "indivRoomPrice": 300,
      "maxTravellers": 8,
      "bookedPlaces": 0,
      "earlyBird": false,
      "promoEarlyBird": 0,
      "lastMinute": false,
      "promoLastMinute": 0,
      "promo": 0,
      "privatized": false,
      "flyTicketPrice": 0
    },
    {
      "departureDate": "2026-03-15T00:00:00",
      "returnDate": "2026-03-28T00:00:00",
      "startingPrice": 1470,
      "indivRoomPrice": 300,
      "maxTravellers": 8,
      "bookedPlaces": 0,
      "earlyBird": false,
      "promoEarlyBird": 0,
      "lastMinute": false,
      "promoLastMinute": 0,
      "promo": 0,
      "privatized": false,
      "flyTicketPrice": 0
    },
    {
      "departureDate": "2026-03-22T00:00:00",
      "returnDate": "2026-04-04T00:00:00",
      "startingPrice": 1470,
      "indivRoomPrice": 300,
      "maxTravellers": 8,
      "bookedPlaces": 5,
      "earlyBird": false,
      "promoEarlyBird": 0,
      "lastMinute": false,
      "promoLastMinute": 0,
      "promo": 0,
      "privatized": false,
      "flyTicketPrice": 0
    },
    {
      "departureDate": "2026-03-29T00:00:00",
      "returnDate": "2026-04-11T00:00:00",
      "startingPrice": 1470,
      "indivRoomPrice": 300,
      "maxTravellers": 8,
      "bookedPlaces": 0,
      "earlyBird": false,
      "promoEarlyBird": 0,
      "lastMinute": false,
      "promoLastMinute": 0,
      "promo": 0,
      "privatized": false,
      "flyTicketPrice": 0
    },
    {
      "departureDate": "2026-04-05T00:00:00",
      "returnDate": "2026-04-18T00:00:00",
      "startingPrice": 1470,
      "indivRoomPrice": 300,
      "maxTravellers": 8,
      "bookedPlaces": 6,
      "earlyBird": false,
      "promoEarlyBird": 0,
      "lastMinute": false,
      "promoLastMinute": 0,
      "promo": 0,
      "privatized": false,
      "flyTicketPrice": 0
    },
    {
      "departureDate": "2026-04-12T00:00:00",
      "returnDate": "2026-04-25T00:00:00",
      "startingPrice": 1470,
      "indivRoomPrice": 300,
      "maxTravellers": 8,
      "bookedPlaces": 0,
      "earlyBird": false,
      "promoEarlyBird": 0,
      "lastMinute": false,
      "promoLastMinute": 0,
      "promo": 0,
      "privatized": false,
      "flyTicketPrice": 0
    },
    {
      "departureDate": "2026-04-19T00:00:00",
      "returnDate": "2026-05-02T00:00:00",
      "startingPrice": 1470,
      "indivRoomPrice": 300,
      "maxTravellers": 8,
      "bookedPlaces": 6,
      "earlyBird": false,
      "promoEarlyBird": 0,
      "lastMinute": false,
      "promoLastMinute": 0,
      "promo": 0,
      "privatized": false,
      "flyTicketPrice": 0
    },
    {
      "departureDate": "2026-04-26T00:00:00",
      "returnDate": "2026-05-09T00:00:00",
      "startingPrice": 1470,
      "indivRoomPrice": 300,
      "maxTravellers": 8,
      "bookedPlaces": 0,
      "earlyBird": false,
      "promoEarlyBird": 0,
      "lastMinute": false,
      "promoLastMinute": 0,
      "promo": 0,
      "privatized": false,
      "flyTicketPrice": 0
    },
    {
      "departureDate": "2026-05-03T00:00:00",
      "returnDate": "2026-05-16T00:00:00",
      "startingPrice": 1470,
      "indivRoomPrice": 300,
      "maxTravellers": 8,
      "bookedPlaces": 0,
      "earlyBird": false,
      "promoEarlyBird": 0,
      "lastMinute": false,
      "promoLastMinute": 0,
      "promo": 0,
      "privatized": false,
      "flyTicketPrice": 0
    },
    {
      "departureDate": "2026-05-10T00:00:00",
      "returnDate": "2026-05-23T00:00:00",
      "startingPrice": 1470,
      "indivRoomPrice": 300,
      "maxTravellers": 8,
      "bookedPlaces": 0,
      "earlyBird": false,
      "promoEarlyBird": 0,
      "lastMinute": false,
      "promoLastMinute": 0,
      "promo": 0,
      "privatized": false,
      "flyTicketPrice": 0
    },
    {
      "departureDate": "2026-05-17T00:00:00",
      "returnDate": "2026-05-30T00:00:00",
      "startingPrice": 1470,
      "indivRoomPrice": 300,
      "maxTravellers": 8,
      "bookedPlaces": 0,
      "earlyBird": false,
      "promoEarlyBird": 0,
      "lastMinute": false,
      "promoLastMinute": 0,
      "promo": 0,
      "privatized": false,
      "flyTicketPrice": 0
    },
    {
      "departureDate": "2025-09-27T00:00:00",
      "returnDate": "2025-10-10T00:00:00",
      "startingPrice": 1460,
      "indivRoomPrice": 300,
      "maxTravellers": 8,
      "bookedPlaces": 0,
      "earlyBird": false,
      "promoEarlyBird": 0,
      "lastMinute": false,
      "promoLastMinute": 0,
      "promo": 0,
      "privatized": false,
      "flyTicketPrice": 0
    },
    {
      "departureDate": "2025-10-20T00:00:00",
      "returnDate": "2025-11-02T00:00:00",
      "startingPrice": 1460,
      "indivRoomPrice": 300,
      "maxTravellers": 8,
      "bookedPlaces": 0,
      "earlyBird": false,
      "promoEarlyBird": 0,
      "lastMinute": false,
      "promoLastMinute": 0,
      "promo": 0,
      "privatized": false,
      "flyTicketPrice": 0
    }
  ]
}