{
  "title": "Voyage initiatique en Inde Himalaya",
  "slug": "voyage-initiatique-inde-karma-yoga",
  "iso": "IN",
  "imgSrc2": {
    "src": "/images/voyages/voyage-initiatique-inde-karma-yoga/mBp5qYBQDmXcS8tevnn7.jpg",
    "alt": "mBp5qYBQDmXcS8tevnn7"
  },
  "imgSrc1": {
    "src": "/images/voyages/voyage-initiatique-inde-karma-yoga/mBp5qYBQDmXcS8tevnn7.jpg",
    "alt": "mBp5qYBQDmXcS8tevnn7"
  },
  "country": "Inde",
  "zoneChapka": 2,
  "privatisationAvailable": false,
  "groupeAvailable": false,
  "duration": "14 jours",
  "startingPrice": 3685,
  "rating": 0,
  "comments": 0,
  "tooltipChild": "",
  "tooltipGroup": "",
  "dates": []
}