{
  "author": "Laurent",
  "authorAge": "",
  "photo": "",
  "rating": 5,
  "text": "Choisi par hasard pour les valeurs et l'état d'esprit, promesses tenues. L’authenticité a été au RV et avons pu compter sur de bons conseils et la réactivité avant et pendant notre voyage. Le soucis du suivi et du bon déroulement des expériences ont été constants. Merci pour tout.",
  "date": "2025-03-25T00:00:00",
  "voyageSlug": "voyage-etude-dauphins-grece",
  "voyageTitle": "Observez les dauphins avec un biologiste marin en Grèce",
  "isOnHome": false
}